verbolab/__init__.py
verbolab-0.0.2.dist-info/METADATA
verbolab-0.0.2.dist-info/WHEEL
verbolab-0.0.2.dist-info/top_level.txt
verbolab-0.0.2.dist-info/RECORD
