Metadata-Version: 2.1
Name: verbolab
Version: 0.0.2
Requires-Dist: wikipedia
Requires-Dist: wget
Requires-Dist: llama-cpp-python
